CHANGES.rst
CONTRIBUTORS.rst
LICENSE.txt
MANIFEST.in
README.rst
setup.py
docs/Makefile
docs/__init__.py
docs/__init__.pyc
docs/conf.py
docs/index.rst
docs/make.bat
docs/nkp_logo.png
docs/propojeni_do_katalogu_nk.rst
docs/requirements.txt
docs/_build/doctrees/environment.pickle
docs/_build/doctrees/index.doctree
docs/_build/doctrees/propojeni_do_katalogu_nk.doctree
docs/_build/doctrees/api/aleph.aleph.doctree
docs/_build/doctrees/api/aleph.doctree
docs/_build/doctrees/api/aleph.export.doctree
docs/_build/doctrees/api/aleph.settings.doctree
docs/_build/doctrees/api/modules.doctree
docs/_build/doctrees/api/datastructures/aleph.datastructures.alephrecord.doctree
docs/_build/doctrees/api/datastructures/aleph.datastructures.convertor.doctree
docs/_build/doctrees/api/datastructures/aleph.datastructures.doctree
docs/_build/doctrees/api/datastructures/aleph.datastructures.epublication.doctree
docs/_build/doctrees/api/datastructures/aleph.datastructures.requests.doctree
docs/_build/doctrees/api/datastructures/aleph.datastructures.results.doctree
docs/_build/doctrees/api/datastructures/aleph.datastructures.semanticinfo.doctree
docs/_build/doctrees/api/datastructures/alephrecord.doctree
docs/_build/doctrees/api/datastructures/author (kopie).doctree
docs/_build/doctrees/api/datastructures/author.doctree
docs/_build/doctrees/api/datastructures/convertor.doctree
docs/_build/doctrees/api/datastructures/datastructures.doctree
docs/_build/doctrees/api/datastructures/eperiodical.doctree
docs/_build/doctrees/api/datastructures/eperiodical_semantic_info.doctree
docs/_build/doctrees/api/datastructures/epublication (kopie).doctree
docs/_build/doctrees/api/datastructures/epublication.doctree
docs/_build/doctrees/api/datastructures/format_enum.doctree
docs/_build/doctrees/api/datastructures/requests.doctree
docs/_build/doctrees/api/datastructures/results.doctree
docs/_build/doctrees/api/datastructures/semanticinfo.doctree
docs/_build/html/.buildinfo
docs/_build/html/genindex.html
src/edeposit.amqp.aleph.egg-info/PKG-INFO
src/edeposit.amqp.aleph.egg-info/SOURCES.txt
src/edeposit.amqp.aleph.egg-info/dependency_links.txt
src/edeposit.amqp.aleph.egg-info/namespace_packages.txt
src/edeposit.amqp.aleph.egg-info/not-zip-safe
src/edeposit.amqp.aleph.egg-info/requires.txt
src/edeposit.amqp.aleph.egg-info/top_level.txt
