Metadata-Version: 1.1
Name: edeposit.amqp.aleph
Version: 1.9.5
Summary: E-Deposit AMQP module providing communication with Aleph
Home-page: https://github.com/edeposit/edeposit.amqp.aleph
Author: Edeposit team
Author-email: edeposit@email.cz
License: MIT
Platform: UNKNOWN
Classifier: Programming Language :: Python :: 2.7
Classifier: License :: OSI Approved :: MIT License
Classifier: Topic :: Software Development :: Libraries :: Python Modules
